watchstat/__init__.py
watchstat/__main__.py
watchstat-1.0.0.dist-info/LICENSE
watchstat-1.0.0.dist-info/METADATA
watchstat-1.0.0.dist-info/WHEEL
watchstat-1.0.0.dist-info/entry_points.txt
watchstat-1.0.0.dist-info/top_level.txt
watchstat-1.0.0.dist-info/RECORD
