Metadata-Version: 2.1
Name: watchstat
Version: 1.0.0
Summary: Execute a command whenever a file's status changes
Home-page: https://github.com/fritzr/watchstat
Author: Fritz Reese
Author-email: fritzoreese@gmail.com
License: UNKNOWN
Project-URL: Issues, https://github.com/fritzr/watchstat/issues
Platform: UNKNOWN
Classifier: Programming Language :: Python
Classifier: License :: OSI Approved :: MIT License
Classifier: Operating System :: OS Independent
Classifier: Topic :: System :: Shells
Classifier: Topic :: Utilities
Requires-Python: >=2.7
